{
  "baseModelDetails": {
    "checkpointFormat": "HUGGINGFACE",
    "defaultPrecision": "PRECISION_UNSPECIFIED",
    "huggingfaceFiles": [
      ".gitattributes",
      ".quant_summary.txt",
      "README.md",
      "chat_template.jinja",
      "config.json",
      "generation_config.json",
      "hf_quant_config.json",
      "model-00001-of-00004.safetensors",
      "model-00002-of-00004.safetensors",
      "model-00003-of-00004.safetensors",
      "model-00004-of-00004.safetensors",
      "model.safetensors.index.json",
      "processor_config.json",
      "tokenizer.json",
      "tokenizer_config.json"
    ],
    "modelType": "gemma4",
    "moe": false,
    "parameterCount": "31000000000",
    "supportsFireattention": true,
    "supportsMtp": false,
    "tunable": false,
    "worldSize": 1
  },
  "calibrated": false,
  "cluster": "",
  "contextLength": 262144,
  "conversationConfig": {
    "style": "",
    "system": "",
    "template": ""
  },
  "createTime": "2026-04-15T00:01:05.241693Z",
  "defaultDraftModel": "",
  "defaultDraftTokenCount": 0,
  "defaultSamplingParams": {},
  "deployedModelRefs": [],
  "deprecationDate": null,
  "description": "Gemma 4 31B IT NVFP4 - NVIDIA 4-bit quantized variant of Google Gemma 4 31B Instruct for efficient inference",
  "displayName": "Gemma 4 31B IT NVFP4",
  "encryptionState": "ENCRYPTION_STATE_UNSPECIFIED",
  "fineTuningJob": "",
  "githubUrl": "",
  "huggingFaceUrl": "https://huggingface.co/nvidia/Gemma-4-31B-IT-NVFP4",
  "importedFrom": "",
  "kind": "HF_BASE_MODEL",
  "name": "accounts/fireworks/models/gemma-4-31b-it-nvfp4",
  "peftDetails": {
    "baseModel": "",
    "baseModelType": "",
    "mergeAddonModelName": "",
    "r": 0,
    "targetModules": []
  },
  "public": true,
  "rlFullParameterTunable": true,
  "rlLoraTunable": true,
  "rlTunable": false,
  "serverlessModes": [],
  "snapshotType": "FULL_SNAPSHOT",
  "state": "READY",
  "status": {
    "code": "OK",
    "message": ""
  },
  "supervisedFullParameterTunable": true,
  "supervisedLoraTunable": true,
  "supportsImageInput": true,
  "supportsLora": false,
  "supportsServerless": false,
  "supportsTools": true,
  "teftDetails": null,
  "trainingContextLength": 131072,
  "tunable": false,
  "updateTime": "2026-07-07T15:18:33.787769Z",
  "useHfApplyChatTemplate": true,
  "useTrainingV2": false
}