{
  "baseModelDetails": {
    "checkpointFormat": "HUGGINGFACE",
    "defaultPrecision": "PRECISION_UNSPECIFIED",
    "huggingfaceFiles": [
      ".gitattributes",
      "README.md",
      "chat_template.jinja",
      "config.json",
      "generation_config.json",
      "model-00001-of-00002.safetensors",
      "model-00002-of-00002.safetensors",
      "model.safetensors.index.json",
      "processor_config.json",
      "tokenizer.json",
      "tokenizer_config.json"
    ],
    "modelType": "gemma4",
    "moe": true,
    "parameterCount": "26000000000",
    "supportsFireattention": false,
    "supportsMtp": false,
    "tunable": false,
    "worldSize": 1
  },
  "calibrated": false,
  "cluster": "",
  "contextLength": 262144,
  "conversationConfig": {
    "style": "",
    "system": "",
    "template": ""
  },
  "createTime": "2026-04-02T05:46:24.892571Z",
  "defaultDraftModel": "",
  "defaultDraftTokenCount": 0,
  "defaultSamplingParams": {},
  "deployedModelRefs": [],
  "deprecationDate": null,
  "description": "Gemma 4 26B A4B IT is a multimodal Mixture-of-Experts model by Google DeepMind with 25.2B total parameters (3.8B active). It supports text and image input with a 256K context window, configurable thinking mode, native function calling, and multilingual support in 140+ languages.",
  "displayName": "Gemma 4 26B A4B IT",
  "encryptionState": "ENCRYPTION_STATE_UNSPECIFIED",
  "fineTuningJob": "",
  "githubUrl": "",
  "huggingFaceUrl": "https://huggingface.co/google/gemma-4-26B-A4B-it",
  "importedFrom": "",
  "kind": "HF_BASE_MODEL",
  "name": "accounts/fireworks/models/gemma-4-26b-a4b-it",
  "peftDetails": {
    "baseModel": "",
    "baseModelType": "",
    "mergeAddonModelName": "",
    "r": 0,
    "targetModules": []
  },
  "public": true,
  "rlFullParameterTunable": true,
  "rlLoraTunable": true,
  "rlTunable": false,
  "serverlessModes": [],
  "snapshotType": "FULL_SNAPSHOT",
  "state": "READY",
  "status": {
    "code": "OK",
    "message": ""
  },
  "supervisedFullParameterTunable": true,
  "supervisedLoraTunable": true,
  "supportsImageInput": true,
  "supportsLora": true,
  "supportsServerless": false,
  "supportsTools": true,
  "teftDetails": null,
  "trainingContextLength": 131072,
  "tunable": false,
  "updateTime": "2026-07-08T16:48:21.245020Z",
  "useHfApplyChatTemplate": false,
  "useTrainingV2": true
}